expsolver
