Metadata-Version: 1.0
Name: expsolver
Version: 0.4
Summary: Expression solver
Home-page: UNKNOWN
Author: UNKNOWN
Author-email: UNKNOWN
License: UNKNOWN
Platform: UNKNOWN
